{
  "name": "WhatsApp Router — IrrigaAgro + AgroManager",
  "nodes": [
    {
      "parameters": {
        "httpMethod": "POST",
        "path": "gotejo-whatsapp",
        "options": {}
      },
      "id": "node_webhook",
      "name": "Webhook Evolution API",
      "type": "n8n-nodes-base.webhook",
      "typeVersion": 1,
      "position": [240, 300],
      "webhookId": "gotejo-whatsapp"
    },
    {
      "parameters": {
        "respondWith": "noData",
        "options": {}
      },
      "id": "node_respond_204",
      "name": "Responder 204 (imediato)",
      "type": "n8n-nodes-base.respondToWebhook",
      "typeVersion": 1,
      "position": [460, 500]
    },
    {
      "parameters": {
        "jsCode": "// Detecta o app de destino pelo número de telefone\n// Lê coluna `app` em whatsapp_contacts: 'irrigaagro' | 'agromanage' | 'ambos'\n\nconst payload = $input.first().json.body;\nconst data = payload.data || payload;\nconst remoteJid = data.key?.remoteJid || '';\nconst phone = remoteJid.replace('@s.whatsapp.net', '').replace('@g.us', '');\nconst fromMe = data.key?.fromMe || false;\n\nif (fromMe || !phone) {\n  return [{ json: { skip: true, phone } }];\n}\n\n// Filtra grupos\nif (remoteJid.endsWith('@g.us')) {\n  return [{ json: { skip: true, phone, reason: 'group' } }];\n}\n\nconst supabaseUrl = $env.SUPABASE_URL;\nconst supabaseKey = $env.SUPABASE_SERVICE_ROLE_KEY;\n\nconst response = await fetch(\n  `${supabaseUrl}/rest/v1/whatsapp_contacts?phone=eq.${phone}&is_active=eq.true&select=id,company_id,app&limit=1`,\n  {\n    headers: {\n      'apikey': supabaseKey,\n      'Authorization': `Bearer ${supabaseKey}`,\n    }\n  }\n);\n\nconst contacts = await response.json();\nconst contact = Array.isArray(contacts) && contacts.length > 0 ? contacts[0] : null;\n\nif (!contact) {\n  return [{ json: { skip: true, phone, reason: 'unknown_number' } }];\n}\n\nconst app = contact.app || 'irrigaagro';\n\n// Para contatos 'ambos': detecta prefixo na mensagem\nlet routeTo = app;\nif (app === 'ambos') {\n  const text = (data.message?.conversation || data.message?.extendedTextMessage?.text || '').toUpperCase().trim();\n  if (text.startsWith('AGRO ') || text === 'AGRO') {\n    routeTo = 'agromanage';\n  } else {\n    routeTo = 'irrigaagro';\n  }\n}\n\nreturn [{ json: { phone, app, routeTo, skip: false, company_id: contact.company_id, payload } }];"
      },
      "id": "node_detect_app",
      "name": "Detectar App",
      "type": "n8n-nodes-base.code",
      "typeVersion": 2,
      "position": [460, 300]
    },
    {
      "parameters": {
        "conditions": {
          "options": { "caseSensitive": true, "typeValidation": "strict" },
          "conditions": [
            {
              "id": "cond_skip",
              "leftValue": "={{ $json.skip }}",
              "rightValue": false,
              "operator": { "type": "boolean", "operation": "equals" }
            }
          ],
          "combinator": "and"
        }
      },
      "id": "node_if_skip",
      "name": "Mensagem válida?",
      "type": "n8n-nodes-base.if",
      "typeVersion": 2,
      "position": [680, 300]
    },
    {
      "parameters": {
        "conditions": {
          "options": { "caseSensitive": true, "typeValidation": "strict" },
          "conditions": [
            {
              "id": "cond_irrigaagro",
              "leftValue": "={{ $json.routeTo }}",
              "rightValue": "irrigaagro",
              "operator": { "type": "string", "operation": "equals" }
            }
          ],
          "combinator": "and"
        }
      },
      "id": "node_if_app",
      "name": "É IrrigaAgro?",
      "type": "n8n-nodes-base.if",
      "typeVersion": 2,
      "position": [900, 220]
    },
    {
      "parameters": {
        "method": "POST",
        "url": "={{ $env.SUPABASE_URL }}/functions/v1/whatsapp-webhook",
        "authentication": "genericCredentialType",
        "genericAuthType": "httpHeaderAuth",
        "sendBody": true,
        "specifyBody": "json",
        "jsonBody": "={{ JSON.stringify($('Webhook Evolution API').item.json.body) }}",
        "options": {}
      },
      "id": "node_irrigaagro",
      "name": "→ IrrigaAgro (Edge Function)",
      "type": "n8n-nodes-base.httpRequest",
      "typeVersion": 4.2,
      "position": [1120, 140],
      "credentials": {
        "httpHeaderAuth": {
          "id": "cred_supabase_service",
          "name": "Supabase Service Role"
        }
      }
    },
    {
      "parameters": {
        "jsCode": "// Normaliza o payload bruto da Evolution API para o formato IncomingMessage do AgroManager\n\nconst routerData = $input.first().json;\nconst payload = routerData.payload;\nconst data = payload.data || payload;\nconst phone = routerData.phone;\nconst companyId = routerData.company_id; // UUID da empresa no AgroManager\n\n// Detectar tipo da mensagem\nconst msg = data.message || {};\nlet messageType = 'text';\nlet content = '';\nlet mediaUrl = null;\nlet mediaMimeType = null;\n\nif (msg.conversation) {\n  messageType = 'text';\n  content = msg.conversation;\n} else if (msg.extendedTextMessage?.text) {\n  messageType = 'text';\n  content = msg.extendedTextMessage.text;\n} else if (msg.audioMessage) {\n  messageType = 'audio';\n  content = '[áudio]';\n  mediaMimeType = msg.audioMessage.mimetype || 'audio/ogg';\n  // URL para download via Evolution API\n  const messageId = data.key?.id || '';\n  const instance = $env.EVOLUTION_INSTANCE || 'N8N-L24h';\n  mediaUrl = `${$env.EVOLUTION_API_URL}/chat/getBase64FromMediaMessage/${instance}`;\n} else if (msg.imageMessage) {\n  messageType = 'image';\n  content = msg.imageMessage.caption || '[imagem]';\n  mediaMimeType = msg.imageMessage.mimetype || 'image/jpeg';\n  const instance = $env.EVOLUTION_INSTANCE || 'N8N-L24h';\n  mediaUrl = `${$env.EVOLUTION_API_URL}/chat/getBase64FromMediaMessage/${instance}`;\n} else if (msg.documentMessage) {\n  messageType = 'document';\n  content = msg.documentMessage.title || msg.documentMessage.fileName || '[documento]';\n  mediaMimeType = msg.documentMessage.mimetype || 'application/pdf';\n} else {\n  // Tipo não suportado (sticker, reaction, etc.) — pula\n  return [{ json: { skip: true, reason: 'unsupported_type' } }];\n}\n\n// Nome do contato (pushName)\nconst userName = data.pushName || null;\n\n// Montar IncomingMessage\nconst incomingMessage = {\n  channel: 'evolution_api',\n  channel_message_id: data.key?.id || null,\n  phone_number: phone,\n  user_name: userName,\n  empresa_id: companyId,\n  message_type: messageType,\n  content: content,\n  media_url: mediaUrl,\n  media_mime_type: mediaMimeType,\n  // Passar payload original para uso posterior (envio de resposta)\n  _evolution_phone: phone,\n  _evolution_instance: $env.EVOLUTION_INSTANCE || 'N8N-L24h',\n  _evolution_api_url: $env.EVOLUTION_API_URL,\n};\n\nreturn [{ json: incomingMessage }];"
      },
      "id": "node_normalize_agro",
      "name": "Normalizar p/ AgroManager",
      "type": "n8n-nodes-base.code",
      "typeVersion": 2,
      "position": [1120, 340]
    },
    {
      "parameters": {
        "conditions": {
          "options": { "caseSensitive": true, "typeValidation": "strict" },
          "conditions": [
            {
              "id": "cond_skip_norm",
              "leftValue": "={{ $json.skip }}",
              "rightValue": true,
              "operator": { "type": "boolean", "operation": "equals" }
            }
          ],
          "combinator": "and"
        }
      },
      "id": "node_if_skip_norm",
      "name": "Tipo suportado?",
      "type": "n8n-nodes-base.if",
      "typeVersion": 2,
      "position": [1340, 340]
    },
    {
      "parameters": {
        "method": "POST",
        "url": "={{ $env.AGROMANAGER_EDGE_URL }}/functions/v1/message-ingestion",
        "authentication": "genericCredentialType",
        "genericAuthType": "httpHeaderAuth",
        "sendBody": true,
        "specifyBody": "json",
        "jsonBody": "={{ JSON.stringify($json) }}",
        "options": {
          "timeout": 30000
        }
      },
      "id": "node_agromanager_edge",
      "name": "→ AgroManager Edge Function",
      "type": "n8n-nodes-base.httpRequest",
      "typeVersion": 4.2,
      "position": [1560, 280],
      "credentials": {
        "httpHeaderAuth": {
          "id": "cred_agromanager_service",
          "name": "AgroManager Service Role"
        }
      }
    },
    {
      "parameters": {
        "jsCode": "// Envia a resposta da Edge Function de volta ao usuário via Evolution API\n\nconst edgeResponse = $input.first().json;\nconst replyMessage = edgeResponse.reply_message;\n\nif (!replyMessage) {\n  return [{ json: { sent: false, reason: 'no_reply_message' } }];\n}\n\n// Recuperar dados do nó de normalização\nconst normData = $('Normalizar p/ AgroManager').first().json;\nconst phone = normData._evolution_phone;\nconst evolutionApiUrl = normData._evolution_api_url || $env.EVOLUTION_API_URL;\nconst instance = normData._evolution_instance || $env.EVOLUTION_INSTANCE || 'N8N-L24h';\n\nif (!phone || !evolutionApiUrl) {\n  return [{ json: { sent: false, reason: 'missing_phone_or_url' } }];\n}\n\nconst response = await fetch(\n  `${evolutionApiUrl}/message/sendText/${instance}`,\n  {\n    method: 'POST',\n    headers: {\n      'Content-Type': 'application/json',\n      'apikey': $env.EVOLUTION_API_KEY,\n    },\n    body: JSON.stringify({\n      number: phone,\n      text: replyMessage,\n    })\n  }\n);\n\nconst result = await response.json().catch(() => ({}));\n\nreturn [{ json: { sent: true, phone, status: response.status, result } }];"
      },
      "id": "node_send_reply",
      "name": "Enviar Resposta (Evolution)",
      "type": "n8n-nodes-base.code",
      "typeVersion": 2,
      "position": [1780, 280]
    }
  ],
  "connections": {
    "Webhook Evolution API": {
      "main": [
        [
          { "node": "Responder 204 (imediato)", "type": "main", "index": 0 },
          { "node": "Detectar App", "type": "main", "index": 0 }
        ]
      ]
    },
    "Detectar App": {
      "main": [
        [{ "node": "Mensagem válida?", "type": "main", "index": 0 }]
      ]
    },
    "Mensagem válida?": {
      "main": [
        [{ "node": "É IrrigaAgro?", "type": "main", "index": 0 }],
        []
      ]
    },
    "É IrrigaAgro?": {
      "main": [
        [{ "node": "→ IrrigaAgro (Edge Function)", "type": "main", "index": 0 }],
        [{ "node": "Normalizar p/ AgroManager", "type": "main", "index": 0 }]
      ]
    },
    "Normalizar p/ AgroManager": {
      "main": [
        [{ "node": "Tipo suportado?", "type": "main", "index": 0 }]
      ]
    },
    "Tipo suportado?": {
      "main": [
        [],
        [{ "node": "→ AgroManager Edge Function", "type": "main", "index": 0 }]
      ]
    },
    "→ AgroManager Edge Function": {
      "main": [
        [{ "node": "Enviar Resposta (Evolution)", "type": "main", "index": 0 }]
      ]
    }
  },
  "settings": {
    "executionOrder": "v1",
    "saveManualExecutions": true,
    "saveDataSuccessExecution": "all",
    "saveDataErrorExecution": "all"
  },
  "staticData": null,
  "tags": ["whatsapp", "router", "irrigaagro", "agromanager"],
  "_comment": {
    "variaveis_n8n": {
      "SUPABASE_URL": "https://wvwjbzpnujmyvzvadctp.supabase.co (IrrigaAgro — para lookup de contatos)",
      "SUPABASE_SERVICE_ROLE_KEY": "<service role key do IrrigaAgro>",
      "AGROMANAGER_EDGE_URL": "https://orinqcuymgszsyzfbmfy.supabase.co (AgroManager)",
      "EVOLUTION_API_URL": "https://<evolution_host>",
      "EVOLUTION_INSTANCE": "N8N-L24h",
      "EVOLUTION_API_KEY": "<api key da instância>"
    },
    "credenciais_n8n": {
      "Supabase Service Role": "HTTP Header Auth — Authorization: Bearer <irrigaagro_service_role_key>",
      "AgroManager Service Role": "HTTP Header Auth — Authorization: Bearer <agromanager_service_role_key>"
    },
    "logica_roteamento": {
      "irrigaagro": "vai direto para IrrigaAgro edge function (payload bruto)",
      "agromanage": "normaliza → AgroManager Edge Function → envia resposta",
      "ambos": "sem prefixo → IrrigaAgro; prefixo 'AGRO ...' → AgroManager"
    },
    "whatsapp_contacts_app_values": {
      "irrigaagro": "contato usa só IrrigaAgro",
      "agromanage": "contato usa só AgroManager",
      "ambos": "contato usa os dois (prefixo determina destino)"
    },
    "como_atualizar_no_n8n": [
      "1. Acesse https://n8n.br11.com.br",
      "2. Abra o workflow 'WhatsApp Router'",
      "3. Se workflow já existe: abrir cada nó e atualizar o código",
      "4. Se importando: Workflows → Import → cole este JSON",
      "5. Configurar variáveis de ambiente (Settings → Variables)",
      "6. Criar credencial 'AgroManager Service Role' (HTTP Header Auth)",
      "7. Salvar e reativar o workflow"
    ],
    "migration_whatsapp_contacts": "Executar supabase/migrations/whatsapp_multi_app_agromanager.sql no banco do IrrigaAgro para adicionar 'agromanage' ao CHECK constraint"
  }
}
